weekly_calendar/__init__.py
weekly_calendar-0.1.2.dist-info/LICENSE
weekly_calendar-0.1.2.dist-info/METADATA
weekly_calendar-0.1.2.dist-info/WHEEL
weekly_calendar-0.1.2.dist-info/top_level.txt
weekly_calendar-0.1.2.dist-info/RECORD
