Metadata-Version: 2.1
Name: weekly-calendar
Version: 0.1.2
Summary: A simple library to deal with weekly opening hours and other recurrent weekly events
Home-page: https://github.com/kardaj/weekly-calendar
Author: kardaj
Author-email: bensalemhsn@gmail.com
License: UNKNOWN
Platform: UNKNOWN
Classifier: Programming Language :: Python :: 2
Classifier: License :: OSI Approved :: MIT License
Classifier: Operating System :: OS Independent
Requires-Dist: pytz
Requires-Dist: tzlocal
